carpy/__init__.py
carpy/aerodynamics/__init__.py
carpy/aerodynamics/_common.py
carpy/aerodynamics/_soln2d_potentialflow.py
carpy/aerodynamics/_soln2d_thinaerofoils.py
carpy/aerodynamics/_soln2d_vortexsource.py
carpy/aerodynamics/_soln3d_liftingline.py
carpy/aerodynamics/_solns_gudmundsson.py
carpy/aerodynamics/_solns_hoerner.py
carpy/aerodynamics/_solns_raymer.py
carpy/conceptualdesign/__init__.py
carpy/conceptualdesign/_airworthiness.py
carpy/conceptualdesign/_constraints.py
carpy/conceptualdesign/_vehicles.py
carpy/environment/__init__.py
carpy/environment/_airports.py
carpy/environment/_atmospheres.py
carpy/environment/_weather.py
carpy/environment/data/1954-ICAO.xlsx
carpy/environment/data/1976-US_standard.xlsx
carpy/environment/data/ISO-2533-1975.xlsx
carpy/environment/data/MIL-HDBK-310_profiles.xlsx
carpy/environment/data/ourairports/airports.csv
carpy/environment/data/ourairports/definitions.xlsx
carpy/environment/data/ourairports/runways.csv
carpy/gaskinetics/__init__.py
carpy/gaskinetics/_chemistry_elements.py
carpy/gaskinetics/_chemistry_molecules.py
carpy/gaskinetics/_dynamics_ideal.py
carpy/gaskinetics/_equations_of_state.py
carpy/gaskinetics/data/bond_forceconstants.yaml
carpy/gaskinetics/data/bond_lengths.yaml
carpy/gaskinetics/data/bond_strengths.yaml
carpy/gaskinetics/data/molecule_criticalpoints.xlsx
carpy/geometry/__init__.py
carpy/geometry/_aerofoils.py
carpy/geometry/_aerofoils_generators.py
carpy/geometry/_ansatz.py
carpy/geometry/_indexing.py
carpy/geometry/_wingplanes.py
carpy/propulsion/__init__.py
carpy/propulsion/_enginedecks_ansatz.py
carpy/propulsion/_network.py
carpy/propulsion/components/__init__.py
carpy/propulsion/components/_common.py
carpy/propulsion/components/_power_raise.py
carpy/propulsion/data/cycling_exhaustion_malewicki.xlsx
carpy/propulsion/data/cyclinganalytics_power.xlsx
carpy/utility/__init__.py
carpy/utility/_constants.py
carpy/utility/_graphtheory.py
carpy/utility/_maths.py
carpy/utility/_miscellaneous.py
carpy-0.0.6.post3.dist-info/LICENSE
carpy-0.0.6.post3.dist-info/METADATA
carpy-0.0.6.post3.dist-info/WHEEL
carpy-0.0.6.post3.dist-info/top_level.txt
carpy-0.0.6.post3.dist-info/RECORD
