Metadata-Version: 2.1
Name: carpy
Version: 0.0.6.post3
Summary: Consolidated aircraft recipes in Python.
Author-email: Yaseen Reza <yaseen605@gmail.com>
Project-URL: homepage, https://github.com/yaseen157/carpy
Project-URL: documentation, https://pypi.org/project/carpy/
Classifier: Development Status :: 3 - Alpha
Classifier: Intended Audience :: Developers
Classifier: Programming Language :: Python :: 3
Classifier: Topic :: Scientific/Engineering
Requires-Python: >=3.9.5
License-File: LICENSE
Requires-Dist: fsspec
Requires-Dist: matplotlib
Requires-Dist: numpy
Requires-Dist: openpyxl
Requires-Dist: pandas
Requires-Dist: periodictable
Requires-Dist: pytest >=7
Requires-Dist: python-metar
Requires-Dist: pyyaml
Requires-Dist: requests
Requires-Dist: sectionproperties
Requires-Dist: scipy
Requires-Dist: setuptools >=67.0.0
Requires-Dist: sympy
Provides-Extra: ipynb
Requires-Dist: jupyter ; extra == 'ipynb'
Requires-Dist: notebook ; extra == 'ipynb'
